{"name":"Message Queue Client Framework","tagline":"消息队列客户端框架（Apache Kafka & Apache ActiveMQ）","body":"Message Queue Client Framework\r\n==============================\r\n\r\n  消息队列客户端框架（Apache Kafka &amp; Apache ActiveMQ）\r\n  * [Release](#release)\r\n  * [Documentation](#documentation)\r\n  * [Producer](#producer)\r\n  * [Consumer](#consumer)\r\n  * [Listener](#listener)\r\n  * [Factory](#factory)\r\n\r\n## Release\r\n\r\n[messagequeue-framework-1.0.jar](https://github.com/DarkPhoenixs/message-queue-client-framework/blob/master/release/messagequeue-framework-1.0.jar?raw=true) (2015-06-01) \r\n\r\n## Documentation\r\n\r\nAPI documentation is available at\r\n\r\n## Producer\r\n\r\n![image](https://raw.githubusercontent.com/DarkPhoenixs/message-queue-client-framework/master/uml/producer.jpg)\r\n\r\n## Consumer\r\n\r\n![image](https://raw.githubusercontent.com/DarkPhoenixs/message-queue-client-framework/master/uml/consumer.jpg)\r\n\r\n## Listener\r\n\r\n![image](https://raw.githubusercontent.com/DarkPhoenixs/message-queue-client-framework/master/uml/listener.jpg)\r\n\r\n## Factory\r\n\r\n![image](https://raw.githubusercontent.com/DarkPhoenixs/message-queue-client-framework/master/uml/factory.jpg)\r\n\r\nFactory config with spring\r\n```xml\r\n<!-- Message Producer Factory -->\r\n<bean id=\"messageProducerFactory\" class=\"org.darkphoenixs.mq.common.MessageProducerFactory\" \r\n  destroy-method=\"destroy\">\r\n    <property name=\"producers\"> \r\n        <array> \r\n            <ref bean=\"messageProducer\" /> \r\n        </array> \r\n    </property> \r\n</bean> \r\n\r\n<!-- Message Consumer Factory  -->\r\n<bean id=\"messageConsumerFactory\" class=\"org.darkphoenixs.mq.common.MessageConsumerFactory\" \r\n  destroy-method=\"destroy\">\r\n    <property name=\"consumers\"> \r\n        <array> \r\n            <ref bean=\"messageConsumer\" /> \r\n        </array>\r\n    </property> \r\n</bean>\r\n```\r\n","google":"","note":"Don't delete this file! It's used internally to help with page regeneration."}